<?xml version="1.0" encoding="utf-8" ?>
<dwsync>
<file name="molly_durst_web_designer.png" server="mollymadegraphics.com" local="132550415400000000" remote="132550415400000000" Dst="1" />
<file name="profile_pic.jpg" server="mollymadegraphics.com" local="132550416000000000" remote="132550416000000000" Dst="1" />
<file name="vs_stone_storefront.JPG" server="mollymadegraphics.com" local="132550416000000000" remote="132550416000000000" Dst="1" />
<file name="booklist.JPG" server="mollymadegraphics.com" local="132550415400000000" remote="132550415400000000" Dst="1" />
<file name="molly_durst_web_designer_2.png" server="mollymadegraphics.com" local="133132068749552181" remote="133131997200000000" Dst="1" />
<file name="molly_durst_web_designer_2.psd" server="mollymadegraphics.com" local="133132066391896429" remote="133131998400000000" Dst="1" />
<file name="profile_pic_2.jpg" server="mollymadegraphics.com" local="131999066610000000" remote="133132005600000000" Dst="1" />
<file name="Molly_Durst_Resume.pdf" server="mollymadegraphics.com" local="133063789667654207" remote="133132069200000000" Dst="1" />
</dwsync>